hal/__init__.py
hal/_initialize.py
hal/exceptions.py
hal/py.typed
hal/version.py
hal/simulation/__init__.py
hal/simulation/main.cpp
hal/simulation/resethandles.cpp
hal/simulation/sim_cb.h
hal/simulation/sim_value_cb.h
hal/src/hal.cpp
hal/_init__wpiHal.py
hal/_wpiHal.cpython-310-x86_64-linux-gnu.so
hal/_wpiHal.pyi
hal/wpihal.pc
hal/simulation/_init__simulation.py
hal/simulation/_simulation.cpython-310-x86_64-linux-gnu.so
hal/simulation/_simulation.pyi
hal/simulation/hal_simulation.pc
hal/trampolines/__HAL_AddressableLEDData.hpp
hal/trampolines/__HAL_CANStreamMessage.hpp
hal/trampolines/__HAL_ControlWord.hpp
hal/trampolines/__HAL_JoystickAxes.hpp
hal/trampolines/__HAL_JoystickButtons.hpp
hal/trampolines/__HAL_JoystickDescriptor.hpp
hal/trampolines/__HAL_JoystickPOVs.hpp
hal/trampolines/__HAL_MatchInfo.hpp
hal/trampolines/__HAL_PowerDistributionFaults.hpp
hal/trampolines/__HAL_PowerDistributionStickyFaults.hpp
hal/trampolines/__HAL_PowerDistributionVersion.hpp
hal/trampolines/__HAL_REVPHCompressorConfig.hpp
hal/trampolines/__HAL_REVPHFaults.hpp
hal/trampolines/__HAL_REVPHStickyFaults.hpp
hal/trampolines/__HAL_REVPHVersion.hpp
hal/trampolines/hal__SimBoolean.hpp
hal/trampolines/hal__SimDevice.hpp
hal/trampolines/hal__SimDouble.hpp
hal/trampolines/hal__SimEnum.hpp
hal/trampolines/hal__SimInt.hpp
hal/trampolines/hal__SimLong.hpp
hal/trampolines/hal__SimValue.hpp
hal/simulation/trampolines/__HALSIM_NotifierInfo.hpp
robotpy_hal-2025.3.2.3.dist-info/METADATA
robotpy_hal-2025.3.2.3.dist-info/WHEEL
robotpy_hal-2025.3.2.3.dist-info/entry_points.txt
robotpy_hal-2025.3.2.3.dist-info/RECORD
